xTerm/Alpha.py
xTerm/Terminal.py
xTerm/__init__.py
xTerm/_utils.py
xTerm-1.6.6.dist-info/METADATA
xTerm-1.6.6.dist-info/WHEEL
xTerm-1.6.6.dist-info/top_level.txt
xTerm-1.6.6.dist-info/RECORD
