Metadata-Version: 2.1
Name: xTerm
Version: 1.6.6
Summary: Professional modding to the terminal and changing the font of string texts
Home-page: https://github.com/xTerm/xTerm
Author: Mmdrza
Author-email: Pymmdrza@gmail.com
License: MIT
Classifier: Programming Language :: Python :: 3
Classifier: License :: OSI Approved :: MIT License
Classifier: Operating System :: OS Independent
Requires-Python: >=3.7
